{
  "brandName": "AIFit.pro",
  "title": "",
  "company": {
    "name": "AIFit.pro",
    "url": "https://phoenixcoded.net",
    "socialLink": {
      "linkedin": "https://in.linkedin.com/company/phoenixcoded",
      "instagram": "#",
      "facebook": "https://www.facebook.com/Phoenixcoded/",
      "youtube": "https://www.youtube.com/@Phoenixcoded",
      "github": "https://github.com/phoenixcoded",
      "dribble": "https://dribbble.com/Phoenixcoded",
      "discord": "https://discord.gg/gmqz4BWYA8",
      "support": "https://support.phoenixcoded.net"
    }
  },
  "logo": {
    "main": "assets/images/graphics/ai/logo1.png",
    "logoIcon": "assets/images/graphics/ai/logo2.png",
    "logoFab": "",
    "logoWatermark": ""
  }
}
